simiq_mcp/__init__.py
simiq_mcp/__main__.py
simiq_mcp-0.0.2.dist-info/METADATA
simiq_mcp-0.0.2.dist-info/WHEEL
simiq_mcp-0.0.2.dist-info/entry_points.txt
simiq_mcp-0.0.2.dist-info/RECORD
