Metadata-Version: 2.4
Name: simiq-mcp
Version: 0.0.2
Summary: MCP server for the ChipIQ "simiq" tool
Project-URL: Documentation, https://github.com/ChipIQ/simiq-mcp#readme
Project-URL: Issues, https://github.com/ChipIQ/chipiq/issues
Project-URL: Source, https://github.com/ChipIQ/chipiq
Author-email: Hans Bouwmeester <hans.bouwmeester@icloud.com>, Asav Gandhi <asavgandhi01@gmail.com>
Classifier: Operating System :: OS Independent
Classifier: Programming Language :: Python
Classifier: Programming Language :: Python :: 3.13
Requires-Python: >=3.13
Requires-Dist: chipiq>=0.0.3
Requires-Dist: mcp~=1.8.0
Requires-Dist: uvicorn>=0.38.0
